CHANGELOG.txt
LICENSE.txt
MANIFEST.in
README.txt
setup.py
juddasTALib/__init__.py
juddasTALib.egg-info/PKG-INFO
juddasTALib.egg-info/SOURCES.txt
juddasTALib.egg-info/dependency_links.txt
juddasTALib.egg-info/requires.txt
juddasTALib.egg-info/top_level.txt