Metadata-Version: 2.1
Name: juddasTALib
Version: 0.0.1
Summary: Just another technical analysis indicator lib
Home-page: 
Author: Paul Judd
Author-email: 
License: MIT
Keywords: TA,indicators,technical analysis,trading,finance
Classifier: Development Status :: 5 - Production/Stable
Classifier: Intended Audience :: Education
Classifier: License :: OSI Approved :: MIT License
Classifier: Programming Language :: Python :: 3
Requires-Python: >=3.6
License-File: LICENSE.txt
